[
    {
      "id": 1,
      "title": "Lumaki Labs Inc.",
      "position": "Software Engineer Intern",
      "description": "As a software engineer at Lumaki Labs Inc, you will work with a creative team and a senior engineer to build out the front end…",
      "duration": "2-months",
      "level":"Intermediate",
      "date": "Oct 1, 2020 EDT",
      "logo": "/static/media/lumaki-logo.19c0a241.png"
   }, {
      "id": 2,
      "title": "University of Toronto",
      "position": "UX/UI Design Intern",
      "description": "As a UX/UI Design at the University of Toronto, you will work directly with professors and researchers to find insights into remote...",
      "duration": "4-months",
      "level":"Beginner",
      "date": "Jan. 1, 2020 EDT",
      "logo": ""
   }
   ]
 